swarmsim/__init__.py
swarmsim/.dev/__init__.py
swarmsim/.dev/archive_analysis.py
swarmsim/.dev/augment.py
swarmsim/agent/Agent.py
swarmsim/agent/DiffDriveAgent.py
swarmsim/agent/DroneAgent.py
swarmsim/agent/MazeAgent.py
swarmsim/agent/ModeSwitchingAgent.py
swarmsim/agent/StaticAgent.py
swarmsim/agent/UnicycleAgent.py
swarmsim/agent/__init__.py
swarmsim/agent/control/AbstractController.py
swarmsim/agent/control/AgentMethodController.py
swarmsim/agent/control/BinaryController.py
swarmsim/agent/control/Controller.py
swarmsim/agent/control/HomogeneousController.py
swarmsim/agent/control/HumanController.py
swarmsim/agent/control/LevyController.py
swarmsim/agent/control/StaticController.py
swarmsim/agent/control/__init__.py
swarmsim/cache/ExternalSimulationArchive.py
swarmsim/cache/__init__.py
swarmsim/config/OutputTensorConfig.py
swarmsim/config/ResultsConfig.py
swarmsim/config/__init__.py
swarmsim/gui/__init__.py
swarmsim/gui/abstractGUI.py
swarmsim/gui/agentGUI.py
swarmsim/gui/connectivityGUI.py
swarmsim/gui/controllerGUI.py
swarmsim/gui/fullControlGUI.py
swarmsim/gui/fonts/JetBrainsMono-AUTHORS.txt
swarmsim/gui/fonts/JetBrainsMono-Bold.ttf
swarmsim/gui/fonts/JetBrainsMono-BoldItalic.ttf
swarmsim/gui/fonts/JetBrainsMono-Italic.ttf
swarmsim/gui/fonts/JetBrainsMono-OFL.txt
swarmsim/gui/fonts/JetBrainsMono-Regular.ttf
swarmsim/gui/fonts/JetBrainsMono-SemiBold.ttf
swarmsim/gui/fonts/JetBrainsMono-SemiBoldItalic.ttf
swarmsim/metrics/AbstractMetric.py
swarmsim/metrics/AgentsAtGoal.py
swarmsim/metrics/Aggregation.py
swarmsim/metrics/AlgebraicConnectivity.py
swarmsim/metrics/AngularMomentum.py
swarmsim/metrics/AverageSpeed.py
swarmsim/metrics/BehaviorFactory.py
swarmsim/metrics/BerlingerCircularity.py
swarmsim/metrics/Centroid.py
swarmsim/metrics/CirclePacking.py
swarmsim/metrics/Circliness.py
swarmsim/metrics/ConvexHull.py
swarmsim/metrics/DelaunayDiffusion.py
swarmsim/metrics/Dispersion.py
swarmsim/metrics/DistanceSizeRatio.py
swarmsim/metrics/DistanceToGoal.py
swarmsim-1.2.2.dist-info/METADATA
swarmsim-1.2.2.dist-info/WHEEL
swarmsim-1.2.2.dist-info/licenses/LICENSE
swarmsim-1.2.2.dist-info/RECORD
