Metadata-Version: 2.4
Name: swarmsim
Version: 1.2.2
Summary: An agent-based swarm simulator.
Project-URL: Homepage, https://github.com/kenblu24/RobotSwarmSimulator
Project-URL: Bug Tracker, https://github.com/kenblu24/RobotSwarmSimulator/issues
Author-email: Connor Mattson <c.mattson@utah.edu>, kenblu24 <kenblu24@hotmail.com>
Maintainer-email: kenblu24 <kenblu24@hotmail.com>
License-Expression: MIT
License-File: LICENSE
Keywords: agent-based,robotics,simulator,swarm
Classifier: Development Status :: 3 - Alpha
Classifier: Operating System :: OS Independent
Classifier: Programming Language :: Python :: 3
Classifier: Topic :: Scientific/Engineering
Requires-Python: >=3.12
Requires-Dist: circle-fit
Requires-Dist: matplotlib
Requires-Dist: numpy
Requires-Dist: opencv-python
Requires-Dist: pandas
Requires-Dist: pillow
Requires-Dist: pygame-ce
Requires-Dist: pyyaml>=6.0.1
Requires-Dist: quads
Requires-Dist: ripser
Requires-Dist: scikit-learn
Requires-Dist: scipy
Requires-Dist: shapely
Requires-Dist: thorpy
Provides-Extra: dev
Requires-Dist: pytest; extra == 'dev'
Requires-Dist: pytest-cov; extra == 'dev'
Requires-Dist: pytest-mock; extra == 'dev'
Requires-Dist: pytest-xdist; extra == 'dev'
Requires-Dist: ruff; extra == 'dev'
Provides-Extra: docs
Requires-Dist: myst-parser; extra == 'docs'
Requires-Dist: numpydoc; extra == 'docs'
Requires-Dist: pydata-sphinx-theme~=0.16.1; extra == 'docs'
Requires-Dist: sphinx; extra == 'docs'
Requires-Dist: sphinx-autodoc-typehints; extra == 'docs'
Requires-Dist: sphinx-copybutton; extra == 'docs'
Requires-Dist: sphinx-design; extra == 'docs'
Requires-Dist: sphinx-togglebutton; extra == 'docs'
Requires-Dist: tqdm; extra == 'docs'
Provides-Extra: shapes
Requires-Dist: pointpats; extra == 'shapes'
